mobetta/__init__.py
mobetta/access.py
mobetta/admin.py
mobetta/base_views.py
mobetta/compat.py
mobetta/ext.py
mobetta/forms.py
mobetta/formsets.py
mobetta/models.py
mobetta/paginators.py
mobetta/urls.py
mobetta/util.py
mobetta/validators.py
mobetta/views.py
mobetta/api/__init__.py
mobetta/api/permissions.py
mobetta/api/serializers.py
mobetta/api/urls.py
mobetta/api/views.py
mobetta/conf/__init__.py
mobetta/conf/settings.py
mobetta/icu/__init__.py
mobetta/icu/admin.py
mobetta/icu/apps.py
mobetta/icu/forms.py
mobetta/icu/mixins.py
mobetta/icu/models.py
mobetta/icu/urls.py
mobetta/icu/utils.py
mobetta/icu/validators.py
mobetta/icu/views.py
mobetta/icu/migrations/0001_initial.py
mobetta/icu/migrations/0002_auto_20170411_0918.py
mobetta/icu/migrations/0003_auto_20170411_0919.py
mobetta/icu/migrations/0004_editlog_messagecomment.py
mobetta/icu/migrations/0005_auto_20170903_0926.py
mobetta/icu/migrations/0006_auto_20180329_1057.py
mobetta/icu/migrations/__init__.py
mobetta/icu/templates/mobetta/icu/file_detail.html
mobetta/icu/templates/mobetta/icu/file_list.html
mobetta/icu/templatetags/__init__.py
mobetta/icu/templatetags/icu_message_tags.py
mobetta/management/__init__.py
mobetta/management/commands/__init__.py
mobetta/management/commands/locate_translation_files.py
mobetta/migrations/0001_initial.py
mobetta/migrations/0002_editlog.py
mobetta/migrations/0003_messagecomment.py
mobetta/migrations/0004_add_msghash_fields.py
mobetta/migrations/0005_populate_msghash.py
mobetta/migrations/0006_msghash_not_null.py
mobetta/migrations/0007_remove_comment_msgid_field.py
mobetta/migrations/0008_auto_20170209_1212.py
mobetta/migrations/0009_auto_20170411_0833.py
mobetta/migrations/0010_auto_20170421_0433.py
mobetta/migrations/0011_auto_20170903_0926.py
mobetta/migrations/0012_auto_20180329_1057.py
mobetta/migrations/__init__.py
mobetta/static/css/file_detail.css
mobetta/static/css/mobetta.css
mobetta-0.3.1.dist-info/DESCRIPTION.rst
mobetta-0.3.1.dist-info/METADATA
mobetta-0.3.1.dist-info/RECORD
mobetta-0.3.1.dist-info/WHEEL
mobetta-0.3.1.dist-info/metadata.json
mobetta-0.3.1.dist-info/top_level.txt
