Metadata-Version: 2.0
Name: mobetta
Version: 0.3.1
Summary: A Django package for managing translation files
Home-page: https://github.com/maykinmedia/mobetta
Author: Maykin Media, Ben Wadsworth
Author-email: ben@maykinmedia.nl
License: BSD
Platform: UNKNOWN
Classifier: Development Status :: 4 - Beta
Classifier: Environment :: Web Environment
Classifier: Framework :: Django
Classifier: Framework :: Django :: 1.11
Classifier: Framework :: Django :: 2.0
Classifier: Intended Audience :: Developers
Classifier: License :: OSI Approved :: BSD License
Classifier: Operating System :: OS Independent
Classifier: Programming Language :: Python
Classifier: Programming Language :: Python :: 2
Classifier: Programming Language :: Python :: 2.7
Classifier: Programming Language :: Python :: 3
Classifier: Programming Language :: Python :: 3.4
Classifier: Programming Language :: Python :: 3.5
Classifier: Programming Language :: Python :: 3.6
Classifier: Topic :: Internet :: WWW/HTTP
Classifier: Topic :: Internet :: WWW/HTTP :: Dynamic Content
Requires-Dist: Django (>=1.11)
Requires-Dist: polib
Requires-Dist: djangorestframework (>=3.7.0)
Provides-Extra: docs
Requires-Dist: Sphinx; extra == 'docs'
Requires-Dist: sphinx-autobuild; extra == 'docs'
Requires-Dist: sphinx-rtd-theme; extra == 'docs'
Provides-Extra: icu
Requires-Dist: PyICU; extra == 'icu'
Provides-Extra: test
Requires-Dist: django-webtest; extra == 'test'
Requires-Dist: factory-boy; extra == 'test'
Requires-Dist: mock; extra == 'test'
Requires-Dist: pytest; extra == 'test'
Requires-Dist: pytest-cov; extra == 'test'
Requires-Dist: pytest-django; extra == 'test'
Requires-Dist: pytest-pep8; extra == 'test'
Requires-Dist: pytest-pylint; extra == 'test'
Requires-Dist: pytest-pythonpath; extra == 'test'
Requires-Dist: pytest-runner; extra == 'test'
